./.gitignore
./.python-version
./LICENSE
./PKG-INFO
./README.md
./downloader.py
./downloader_shared.py
./llms.txt
./pyproject.toml
./requirements.txt
canvas_downloader-0.1.0.dist-info/METADATA
canvas_downloader-0.1.0.dist-info/WHEEL
canvas_downloader-0.1.0.dist-info/entry_points.txt
canvas_downloader-0.1.0.dist-info/licenses/LICENSE
canvas_downloader-0.1.0.dist-info/RECORD
