Metadata-Version: 2.4
Name: canvas_downloader
Version: 0.1.0
Summary: A fast, safe, and customizable CLI tool to download course content from Canvas.
Project-URL: Homepage, https://github.com/jamubc/Canvas_Downloader
Project-URL: Issues, https://github.com/jamubc/Canvas_Downloader/issues
Author: jamubc
License-Expression: MIT
License-File: LICENSE
Classifier: Environment :: Console
Classifier: License :: OSI Approved :: MIT License
Classifier: Operating System :: OS Independent
Classifier: Programming Language :: Python :: 3
Requires-Python: >=3.8
Requires-Dist: beautifulsoup4>=4.12.0
Requires-Dist: html2text>=2024.2.26
Requires-Dist: pathvalidate>=3.2.0
Requires-Dist: pdfkit>=1.0.0
Requires-Dist: requests>=2.32.0
Requires-Dist: tqdm>=4.66.0
